Workbook

Sheet Expenses
B2: Expenses
B3: Recurring = calculated by time period | Static = one-time cost | End Date blank = uses TODAY()
A4: Type | B4: Item Description | C4: Unit Price ($) | D4: Frequency | E4: Start Date | F4: End Date | G4: Total Spent ($) | H4: Receipt Filename | I4: Notes | K4: Expense Calculator
A5: Recurring | B5: Amazon FBA Subscription | C5: 40 | D5: Month | E5: 46134 | G5: =IF(A5="","",IF(A5="Static",C5,IF(D5="Day",C5*(IF(F5="",TODAY(),F5)-E5),IF(D5="Week",C5*((IF(F5="",TODAY(),F5)-E5)/7),IF(D5="Month",C5*(DATEDIF(E5,IF(F5="",TODAY(),F5),"m")+1),IF(D5="Year",C5*(DATEDIF(E5,IF(F5="",TODAY(),F5),"y")+1),0)))))) -> 40 | H5: Amazon Seller confirmation Email April 22 2026 | I5: Paid with Emmanuel Amex | K5: Start Date | L5: 46113
A6: Recurring | B6: Claude Subscription | C6: 20 | D6: Month | E6: 46134 | G6: =IF(A6="","",IF(A6="Static",C6,IF(D6="Day",C6*(IF(F6="",TODAY(),F6)-E6),IF(D6="Week",C6*((IF(F6="",TODAY(),F6)-E6)/7),IF(D6="Month",C6*(DATEDIF(E6,IF(F6="",TODAY(),F6),"m")+1),IF(D6="Year",C6*(DATEDIF(E6,IF(F6="",TODAY(),F6),"y")+1),0)))))) -> 20 | H6: Claude Receipt April 22 2026.pdf | I6: Paid with Emmanuel Amex | K6: End Date | L6: 46364
A7: Recurring | B7: Seller Amp | C7: 299.5 | D7: Month | E7: 46134 | G7: =IF(A7="","",IF(A7="Static",C7,IF(D7="Day",C7*(IF(F7="",TODAY(),F7)-E7),IF(D7="Week",C7*((IF(F7="",TODAY(),F7)-E7)/7),IF(D7="Month",C7*(DATEDIF(E7,IF(F7="",TODAY(),F7),"m")+1),IF(D7="Year",C7*(DATEDIF(E7,IF(F7="",TODAY(),F7),"y")+1),0)))))) -> 299.5
A8: Recurring | B8: Keepa | C8: 340.86 | D8: Month | E8: 46134 | G8: =IF(A8="","",IF(A8="Static",C8,IF(D8="Day",C8*(IF(F8="",TODAY(),F8)-E8),IF(D8="Week",C8*((IF(F8="",TODAY(),F8)-E8)/7),IF(D8="Month",C8*(DATEDIF(E8,IF(F8="",TODAY(),F8),"m")+1),IF(D8="Year",C8*(DATEDIF(E8,IF(F8="",TODAY(),F8),"y")+1),0)))))) -> 340.86 | H8: Keepa Receipt April 22 2026.pdf | K8: Static Total | L8: =SUMIFS(G:G,A:A,"Static",E:E,">="&L5,E:E,"<="&L6) -> 343.96
A9: Recurring | B9: Boxem | C9: 449 | D9: Month | E9: 46134 | G9: =IF(A9="","",IF(A9="Static",C9,IF(D9="Day",C9*(IF(F9="",TODAY(),F9)-E9),IF(D9="Week",C9*((IF(F9="",TODAY(),F9)-E9)/7),IF(D9="Month",C9*(DATEDIF(E9,IF(F9="",TODAY(),F9),"m")+1),IF(D9="Year",C9*(DATEDIF(E9,IF(F9="",TODAY(),F9),"y")+1),0)))))) -> 449 | K9: Recurring Total | L9: {=SUMPRODUCT( (A5:A517="Recurring")* (E5:E517<=L6)* (IF(F5:F517="",TODAY(),F5:F517)>=L5)* C5:C517* IF(D5:D517="Day", ((IF(F5:F517="",TODAY(),F5:F517)*(IF(F5:F517="",TODAY(),F5:F517)<=L6)+L6*(IF(F5:F517="",TODAY(),F5:F517)>L6)) -(E5:E517*(E5:E517>=L5)+L5*(E5:E517<L5))), IF(D5:D517="Week", ((IF(F5:F517="",TODAY(),F5:F517)*(IF(F5:F517="",TODAY(),F5:F517)<=L6)+L6*(IF(F5:F517="",TODAY(),F5:F517)>L6)) -(E5:E517*(E5:E517>=L5)+L5*(E5:E517<L5)))/7, IF(D5:D517="Month", DATEDIF( (E5:E517*(E5:E517>=L5)+L5*(E5:E517<L5)), (IF(F5:F517="",TODAY(),F5:F517)*(IF(F5:F517="",TODAY(),F5:F517)<=L6)+L6*(IF(F5:F517="",TODAY(),F5:F517)>L6)), "m")+1, IF(D5:D517="Year", DATEDIF( (E5:E517*(E5:E517>=L5)+L5*(E5:E517<L5)), (IF(F5:F517="",TODAY(),F5:F517)*(IF(F5:F517="",TODAY(),F5:F517)<=L6)+L6*(IF(F5:F517="",TODAY(),F5:F517)>L6)), "y")+1, 0)))))} -> 1328.36
A10: Recurring | B10: Seller Board | C10: 179 | D10: Month | E10: 46134 | G10: =IF(A10="","",IF(A10="Static",C10,IF(D10="Day",C10*(IF(F10="",TODAY(),F10)-E10),IF(D10="Week",C10*((IF(F10="",TODAY(),F10)-E10)/7),IF(D10="Month",C10*(DATEDIF(E10,IF(F10="",TODAY(),F10),"m")+1),IF(D10="Year",C10*(DATEDIF(E10,IF(F10="",TODAY(),F10),"y")+1),0)))))) -> 179 | K10: All Total | L10: =SUM(L8:L9) -> 1672.32
A11: Static | B11: Frontier Co-Op | C11: 10 | D11: Once | E11: 46135 | G11: =IF(A11="","",IF(A11="Static",C11,IF(D11="Day",C11*(IF(F11="",TODAY(),F11)-E11),IF(D11="Week",C11*((IF(F11="",TODAY(),F11)-E11)/7),IF(D11="Month",C11*(DATEDIF(E11,IF(F11="",TODAY(),F11),"m")+1),IF(D11="Year",C11*(DATEDIF(E11,IF(F11="",TODAY(),F11),"y")+1),0)))))) -> 10 | I11: $10/Lifetime access
A12: Static | B12: Neo Email Setup | C12: 35.76 | D12: Once | E12: 46136 | G12: =IF(A12="","",IF(A12="Static",C12,IF(D12="Day",C12*(IF(F12="",TODAY(),F12)-E12),IF(D12="Week",C12*((IF(F12="",TODAY(),F12)-E12)/7),IF(D12="Month",C12*(DATEDIF(E12,IF(F12="",TODAY(),F12),"m")+1),IF(D12="Year",C12*(DATEDIF(E12,IF(F12="",TODAY(),F12),"y")+1),0)))))) -> 35.76 | H12: Neo Email Setup Receipt April 24 2026.pdf | I12: $35.76 / 2 years | K12: ⚠ Yellow = your inputs | Black = calculated formula | Colored = type indicator
A13: Static | B13: NameCheap Domain Purchase | C13: 26.36 | D13: Once | E13: 46136 | G13: =IF(A13="","",IF(A13="Static",C13,IF(D13="Day",C13*(IF(F13="",TODAY(),F13)-E13),IF(D13="Week",C13*((IF(F13="",TODAY(),F13)-E13)/7),IF(D13="Month",C13*(DATEDIF(E13,IF(F13="",TODAY(),F13),"m")+1),IF(D13="Year",C13*(DATEDIF(E13,IF(F13="",TODAY(),F13),"y")+1),0)))))) -> 26.36 | H13: NameCheap Domain Purchase Receipt April 24 2026.pdf | I13: $26.36 / 2 years
A14: Static | B14: LLC Creation Expenses | C14: 203 | D14: Once | E14: 46139 | G14: =IF(A14="","",IF(A14="Static",C14,IF(D14="Day",C14*(IF(F14="",TODAY(),F14)-E14),IF(D14="Week",C14*((IF(F14="",TODAY(),F14)-E14)/7),IF(D14="Month",C14*(DATEDIF(E14,IF(F14="",TODAY(),F14),"m")+1),IF(D14="Year",C14*(DATEDIF(E14,IF(F14="",TODAY(),F14),"y")+1),0)))))) -> 203 | H14: LLC Creation Receipt.pdf | I14: $203 for all required forms
A15: Static | B15: 1st Inventory (Yarn) | C15: 68.84 | D15: Once | E15: 46137 | G15: =IF(A15="","",IF(A15="Static",C15,IF(D15="Day",C15*(IF(F15="",TODAY(),F15)-E15),IF(D15="Week",C15*((IF(F15="",TODAY(),F15)-E15)/7),IF(D15="Month",C15*(DATEDIF(E15,IF(F15="",TODAY(),F15),"m")+1),IF(D15="Year",C15*(DATEDIF(E15,IF(F15="",TODAY(),F15),"y")+1),0)))))) -> 68.84 | I15: $68.84 for 2 pack of 12 each
G17: =IF(A17="","",IF(A17="Static",C17,IF(D17="Day",C17*(IF(F17="",TODAY(),F17)-E17),IF(D17="Week",C17*((IF(F17="",TODAY(),F17)-E17)/7),IF(D17="Month",C17*(DATEDIF(E17,IF(F17="",TODAY(),F17),"m")+1),IF(D17="Year",C17*(DATEDIF(E17,IF(F17="",TODAY(),F17),"y")+1),0))))))
G18: =IF(A18="","",IF(A18="Static",C18,IF(D18="Day",C18*(IF(F18="",TODAY(),F18)-E18),IF(D18="Week",C18*((IF(F18="",TODAY(),F18)-E18)/7),IF(D18="Month",C18*(DATEDIF(E18,IF(F18="",TODAY(),F18),"m")+1),IF(D18="Year",C18*(DATEDIF(E18,IF(F18="",TODAY(),F18),"y")+1),0))))))
G36: =IF(A36="","",IF(A36="Static",C36,IF(D36="Day",C36*(IF(F36="",TODAY(),F36)-E36),IF(D36="Week",C36*((IF(F36="",TODAY(),F36)-E36)/7),IF(D36="Month",C36*(DATEDIF(E36,IF(F36="",TODAY(),F36),"m")+1),IF(D36="Year",C36*(DATEDIF(E36,IF(F36="",TODAY(),F36),"y")+1),0))))))
G37: =IF(A37="","",IF(A37="Static",C37,IF(D37="Day",C37*(IF(F37="",TODAY(),F37)-E37),IF(D37="Week",C37*((IF(F37="",TODAY(),F37)-E37)/7),IF(D37="Month",C37*(DATEDIF(E37,IF(F37="",TODAY(),F37),"m")+1),IF(D37="Year",C37*(DATEDIF(E37,IF(F37="",TODAY(),F37),"y")+1),0))))))
G38: =IF(A38="","",IF(A38="Static",C38,IF(D38="Day",C38*(IF(F38="",TODAY(),F38)-E38),IF(D38="Week",C38*((IF(F38="",TODAY(),F38)-E38)/7),IF(D38="Month",C38*(DATEDIF(E38,IF(F38="",TODAY(),F38),"m")+1),IF(D38="Year",C38*(DATEDIF(E38,IF(F38="",TODAY(),F38),"y")+1),0))))))
G39: =IF(A39="","",IF(A39="Static",C39,IF(D39="Day",C39*(IF(F39="",TODAY(),F39)-E39),IF(D39="Week",C39*((IF(F39="",TODAY(),F39)-E39)/7),IF(D39="Month",C39*(DATEDIF(E39,IF(F39="",TODAY(),F39),"m")+1),IF(D39="Year",C39*(DATEDIF(E39,IF(F39="",TODAY(),F39),"y")+1),0))))))
G40: =IF(A40="","",IF(A40="Static",C40,IF(D40="Day",C40*(IF(F40="",TODAY(),F40)-E40),IF(D40="Week",C40*((IF(F40="",TODAY(),F40)-E40)/7),IF(D40="Month",C40*(DATEDIF(E40,IF(F40="",TODAY(),F40),"m")+1),IF(D40="Year",C40*(DATEDIF(E40,IF(F40="",TODAY(),F40),"y")+1),0))))))
G41: =IF(A41="","",IF(A41="Static",C41,IF(D41="Day",C41*(IF(F41="",TODAY(),F41)-E41),IF(D41="Week",C41*((IF(F41="",TODAY(),F41)-E41)/7),IF(D41="Month",C41*(DATEDIF(E41,IF(F41="",TODAY(),F41),"m")+1),IF(D41="Year",C41*(DATEDIF(E41,IF(F41="",TODAY(),F41),"y")+1),0))))))
G42: =IF(A42="","",IF(A42="Static",C42,IF(D42="Day",C42*(IF(F42="",TODAY(),F42)-E42),IF(D42="Week",C42*((IF(F42="",TODAY(),F42)-E42)/7),IF(D42="Month",C42*(DATEDIF(E42,IF(F42="",TODAY(),F42),"m")+1),IF(D42="Year",C42*(DATEDIF(E42,IF(F42="",TODAY(),F42),"y")+1),0))))))
G43: =IF(A43="","",IF(A43="Static",C43,IF(D43="Day",C43*(IF(F43="",TODAY(),F43)-E43),IF(D43="Week",C43*((IF(F43="",TODAY(),F43)-E43)/7),IF(D43="Month",C43*(DATEDIF(E43,IF(F43="",TODAY(),F43),"m")+1),IF(D43="Year",C43*(DATEDIF(E43,IF(F43="",TODAY(),F43),"y")+1),0))))))
G44: =IF(A44="","",IF(A44="Static",C44,IF(D44="Day",C44*(IF(F44="",TODAY(),F44)-E44),IF(D44="Week",C44*((IF(F44="",TODAY(),F44)-E44)/7),IF(D44="Month",C44*(DATEDIF(E44,IF(F44="",TODAY(),F44),"m")+1),IF(D44="Year",C44*(DATEDIF(E44,IF(F44="",TODAY(),F44),"y")+1),0))))))
G45: =IF(A45="","",IF(A45="Static",C45,IF(D45="Day",C45*(IF(F45="",TODAY(),F45)-E45),IF(D45="Week",C45*((IF(F45="",TODAY(),F45)-E45)/7),IF(D45="Month",C45*(DATEDIF(E45,IF(F45="",TODAY(),F45),"m")+1),IF(D45="Year",C45*(DATEDIF(E45,IF(F45="",TODAY(),F45),"y")+1),0))))))
... G518: =IF(A518="","",IF(A518="Static",C518,IF(D518="Day",C518*(IF(F518="",TODAY(),F518)-E518),IF(D518="Week",C518*((IF(F518="",TODAY(),F518)-E518)/7),IF(D518="Month",C518*(DATEDIF(E518,IF(F518="",TODAY(),F518),"m")+1),IF(D518="Year",C518*(DATEDIF(E518,IF(F518="",TODAY(),F518),"y")+1),0))))))

Sheet Amazon Income
B2: Amazon Income
B3: Log each Amazon payout here — one row per deposit
A4: Date | B4: Type | C4: Amount ($) | D4: Notes | F4: Income Calculator
A5: 46139 | B5: Income after Fees | C5: 5000 | D5: Test | F5: Start Date | G5: 46139
F6: End Date | G6: 47359
F8: Net Revenue | G8: =SUMIFS(C:C,A:A,">="&G5,A:A,"<="&G6) -> 5000
F10: # of Deposits | G10: =COUNTA(A5:A10006) -> 1
F12: ⚠ Yellow = date range inputs | Net Revenue auto-updates as you add rows

Sheet Amazon Profit
B2: Amazon Profit Calculator
B3: 🟡 Yellow = your inputs (edit freely) | ⚫ Black = formula (do not edit) | 🟢 Green = live from another sheet
A4: DATE RANGE ← yellow cells are your inputs
A5: Start Date | B5: 46113 | C5: First date to include in calculations
A6: End Date | B6: 46292 | C6: Last date to include in calculations
A8: REVENUE & EXPENSES — do not edit these rows
A9: Revenue | B9: =SUMIFS('Amazon Income'!C:C,'Amazon Income'!A:A,">="&B5,'Amazon Income'!A:A,"<="&B6) -> 5000 | C9: Live from Amazon Income sheet (filtered by date range)
A10: Expenses | B10: {=SUMPRODUCT( (Expenses!E5:E517>=B5)* (IF(Expenses!F5:F517="",TODAY(),Expenses!F5:F517)<=B6)* IF(Expenses!G5:G517="",0,Expenses!G5:G517) )} -> 1672.32 | C10: Live from Expenses sheet (date filtered, handles blank end dates)
A12: PROFIT
A13: Pre-Tax Profit | B13: =B9-B10 -> 3327.68 | C13: Revenue minus all expenses
A15: TAX RESERVE ← edit yellow cell
A16: Tax Rate | B16: 0.35 | C16: ⚠ Edit this — estimated combined federal + NJ rate
A17: Tax Reserve | B17: =IF(B13>0,B13*B16,0) -> 1164.688 | C17: Set aside — do not spend or distribute
A19: REINVESTMENT ← edit yellow cell
A20: Reinvest % | B20: 0.5 | C20: ⚠ Edit this — % of after-tax profit to reinvest
A21: Reinvest Amount | B21: =IF(B13>0,(B13-B17)*B20,0) -> 1081.496 | C21: Reinvested back into inventory or growth
A23: MEMBER DISTRIBUTION ← edit ownership % cells
A24: Distributable Profit | B24: =B13-B17-B21 -> 1081.496 | C24: After deducting tax reserve and reinvestment
A25: Kadiatu % | B25: 0.7 | C25: ⚠ Edit if ownership split changes
A26: Emmanuel % | B26: 0.3 | C26: ⚠ Edit if ownership split changes
A27: Kadiatu Share | B27: =B24*B25 -> 757.0472 | C27: Kadiatu's distributable share
A28: Emmanuel Share | B28: =B24*B26 -> 324.4488 | C28: Emmanuel's distributable share
A30: Ownership check (must = 100%) | B30: =B25+B26 -> 1 | C30: If not 100%, adjust Kadiatu % or Emmanuel % above

Sheet Dashboard
B2: Central Line Group LLC — Finance Overview
B3: EIN: 42-2162254 | NJ ID: 0451453963 | Formed: April 27, 2026
B7: Total Revenue ($) | D7: Total Expenses ($) | E7: Pre-Tax Profit ($)
B8: =SUM('Amazon Income'!C:C) -> 5000 | D8: =SUM(Expenses!G:G) -> 1672.32 | E8: ='Amazon Profit'!B13 -> 3327.68
B11: FINANCIAL SUMMARY
B12: Category | C12: Amount ($) | D12: % of Revenue | E12: Notes
B13: Gross Revenue | C13: =SUM('Amazon Income'!C:C) -> 5000 | D13: 100% | E13: Total Amazon payouts to date
B14: Recurring Expenses | C14: =SUMIF(Expenses!A:A,"Recurring",Expenses!G:G) -> 1328.36 | D14: =C14/C13 -> 0.265672 | E14: Monthly subscriptions & tools
B15: Static / One-time | C15: =SUMIF(Expenses!A:A,"Static",Expenses!G:G) -> 343.96 | D15: =C15/C13 -> 0.068792 | E15: Setup costs, licenses, inventory
B16: Total Expenses | C16: =C14+C15 -> 1672.32 | D16: =C16/C13 -> 0.334464 | E16: Recurring + Static
B17: Pre-Tax Profit | C17: ='Amazon Profit'!B13 -> 3327.68 | D17: =C17/C13 -> 0.665536 | E17: Revenue minus all expenses
B18: Tax Reserve (35%) | C18: ='Amazon Profit'!B17 -> 1164.688 | D18: =C18/C13 -> 0.2329376 | E18: Set aside — do not spend
B19: Reinvestment | C19: ='Amazon Profit'!B21 -> 1081.496 | D19: =C19/C13 -> 0.2162992 | E19: Back into inventory / growth
B20: Distributable Profit | C20: ='Amazon Profit'!B24 -> 1081.496 | D20: =C20/C13 -> 0.2162992 | E20: After tax reserve + reinvestment
B21: Kadiatu (70%) | C21: ='Amazon Profit'!B27 -> 757.0472 | D21: =C21/C13 -> 0.15140944 | E21: Kadiatu's share
B22: Emmanuel (30%) | C22: ='Amazon Profit'!B28 -> 324.4488 | D22: =C22/C13 -> 0.06488976 | E22: Emmanuel's share
